{
  "metadata": {
    "total": 500,
    "level": "A1-A2",
    "description": "500 個西班牙語常用單字（依主題分類）"
  },
  "categories": {
    "問候與寒暄": [
      {"es": "hola", "zh": "你好", "ipa": "ˈola"},
      {"es": "adiós", "zh": "再見", "ipa": "aˈðjos"},
      {"es": "buenos días", "zh": "早安", "ipa": ""},
      {"es": "buenas tardes", "zh": "午安/下午好", "ipa": ""},
      {"es": "buenas noches", "zh": "晚安", "ipa": ""},
      {"es": "gracias", "zh": "謝謝", "ipa": "ˈɡɾaθjas"},
      {"es": "de nada", "zh": "不客氣", "ipa": ""},
      {"es": "por favor", "zh": "請", "ipa": ""},
      {"es": "perdón", "zh": "對不起/打擾一下", "ipa": ""},
      {"es": "lo siento", "zh": "我很抱歉", "ipa": ""},
      {"es": "disculpe", "zh": "不好意思（敬語）", "ipa": ""},
      {"es": "bienvenido", "zh": "歡迎", "ipa": ""},
      {"es": "encantado", "zh": "幸會（男）", "ipa": ""},
      {"es": "encantada", "zh": "幸會（女）", "ipa": ""},
      {"es": "mucho gusto", "zh": "很高興認識你", "ipa": ""},
      {"es": "hasta luego", "zh": "回頭見", "ipa": ""},
      {"es": "hasta mañana", "zh": "明天見", "ipa": ""},
      {"es": "hasta pronto", "zh": "很快見", "ipa": ""},
      {"es": "nos vemos", "zh": "再見/回見", "ipa": ""},
      {"es": "chao", "zh": "再見（口語）", "ipa": ""},
      {"es": "salud", "zh": "乾杯/保重", "ipa": ""},
      {"es": "felicidades", "zh": "恭喜", "ipa": ""},
      {"es": "enhorabuena", "zh": "恭喜", "ipa": ""},
      {"es": "suerte", "zh": "祝好運", "ipa": ""},
      {"es": "ánimo", "zh": "加油", "ipa": ""}
    ],
    "代名詞與人稱": [
      {"es": "yo", "zh": "我", "ipa": "ʝo"},
      {"es": "tú", "zh": "你", "ipa": "tu"},
      {"es": "él", "zh": "他", "ipa": "el"},
      {"es": "ella", "zh": "她", "ipa": "ˈeʝa"},
      {"es": "usted", "zh": "您", "ipa": ""},
      {"es": "nosotros", "zh": "我們", "ipa": ""},
      {"es": "vosotros", "zh": "你們", "ipa": ""},
      {"es": "ellos", "zh": "他們", "ipa": ""},
      {"es": "ellas", "zh": "她們", "ipa": ""},
      {"es": "ustedes", "zh": "您們", "ipa": ""},
      {"es": "me", "zh": "我（受詞）", "ipa": ""},
      {"es": "te", "zh": "你（受詞）", "ipa": ""},
      {"es": "le", "zh": "他/她（間接受詞）", "ipa": ""},
      {"es": "nos", "zh": "我們（受詞）", "ipa": ""},
      {"es": "les", "zh": "他們（間接受詞）", "ipa": ""}
    ],
    "家庭": [
      {"es": "familia", "zh": "家庭", "ipa": "faˈmilja"},
      {"es": "padre", "zh": "父親", "ipa": "ˈpaðɾe"},
      {"es": "madre", "zh": "母親", "ipa": "ˈmaðɾe"},
      {"es": "papá", "zh": "爸爸", "ipa": ""},
      {"es": "mamá", "zh": "媽媽", "ipa": ""},
      {"es": "hijo", "zh": "兒子", "ipa": ""},
      {"es": "hija", "zh": "女兒", "ipa": ""},
      {"es": "hermano", "zh": "兄弟", "ipa": ""},
      {"es": "hermana", "zh": "姊妹", "ipa": ""},
      {"es": "abuelo", "zh": "祖父", "ipa": ""},
      {"es": "abuela", "zh": "祖母", "ipa": ""},
      {"es": "tío", "zh": "叔叔/伯父", "ipa": ""},
      {"es": "tía", "zh": "阿姨/姑姑", "ipa": ""},
      {"es": "primo", "zh": "表兄弟", "ipa": ""},
      {"es": "prima", "zh": "表姊妹", "ipa": ""},
      {"es": "sobrino", "zh": "姪子", "ipa": ""},
      {"es": "sobrina", "zh": "姪女", "ipa": ""},
      {"es": "esposo", "zh": "丈夫", "ipa": ""},
      {"es": "esposa", "zh": "妻子", "ipa": ""},
      {"es": "marido", "zh": "丈夫", "ipa": ""},
      {"es": "novio", "zh": "男朋友", "ipa": ""},
      {"es": "novia", "zh": "女朋友", "ipa": ""},
      {"es": "amigo", "zh": "朋友（男）", "ipa": ""},
      {"es": "amiga", "zh": "朋友（女）", "ipa": ""},
      {"es": "niño", "zh": "男孩/小孩", "ipa": ""},
      {"es": "niña", "zh": "女孩", "ipa": ""},
      {"es": "bebé", "zh": "嬰兒", "ipa": ""},
      {"es": "hombre", "zh": "男人", "ipa": ""},
      {"es": "mujer", "zh": "女人", "ipa": ""},
      {"es": "persona", "zh": "人", "ipa": ""}
    ],
    "數字": [
      {"es": "cero", "zh": "零", "ipa": ""},
      {"es": "uno", "zh": "一", "ipa": ""},
      {"es": "dos", "zh": "二", "ipa": ""},
      {"es": "tres", "zh": "三", "ipa": ""},
      {"es": "cuatro", "zh": "四", "ipa": ""},
      {"es": "cinco", "zh": "五", "ipa": ""},
      {"es": "seis", "zh": "六", "ipa": ""},
      {"es": "siete", "zh": "七", "ipa": ""},
      {"es": "ocho", "zh": "八", "ipa": ""},
      {"es": "nueve", "zh": "九", "ipa": ""},
      {"es": "diez", "zh": "十", "ipa": ""},
      {"es": "once", "zh": "十一", "ipa": ""},
      {"es": "doce", "zh": "十二", "ipa": ""},
      {"es": "trece", "zh": "十三", "ipa": ""},
      {"es": "catorce", "zh": "十四", "ipa": ""},
      {"es": "quince", "zh": "十五", "ipa": ""},
      {"es": "veinte", "zh": "二十", "ipa": ""},
      {"es": "treinta", "zh": "三十", "ipa": ""},
      {"es": "cuarenta", "zh": "四十", "ipa": ""},
      {"es": "cincuenta", "zh": "五十", "ipa": ""},
      {"es": "sesenta", "zh": "六十", "ipa": ""},
      {"es": "setenta", "zh": "七十", "ipa": ""},
      {"es": "ochenta", "zh": "八十", "ipa": ""},
      {"es": "noventa", "zh": "九十", "ipa": ""},
      {"es": "cien", "zh": "一百", "ipa": ""},
      {"es": "mil", "zh": "一千", "ipa": ""},
      {"es": "millón", "zh": "一百萬", "ipa": ""},
      {"es": "primero", "zh": "第一", "ipa": ""},
      {"es": "segundo", "zh": "第二", "ipa": ""},
      {"es": "tercero", "zh": "第三", "ipa": ""}
    ],
    "顏色": [
      {"es": "color", "zh": "顏色", "ipa": ""},
      {"es": "rojo", "zh": "紅色", "ipa": ""},
      {"es": "azul", "zh": "藍色", "ipa": ""},
      {"es": "verde", "zh": "綠色", "ipa": ""},
      {"es": "amarillo", "zh": "黃色", "ipa": ""},
      {"es": "blanco", "zh": "白色", "ipa": ""},
      {"es": "negro", "zh": "黑色", "ipa": ""},
      {"es": "gris", "zh": "灰色", "ipa": ""},
      {"es": "rosa", "zh": "粉紅色", "ipa": ""},
      {"es": "morado", "zh": "紫色", "ipa": ""},
      {"es": "naranja", "zh": "橘色", "ipa": ""},
      {"es": "marrón", "zh": "棕色", "ipa": ""},
      {"es": "café", "zh": "咖啡色", "ipa": ""},
      {"es": "dorado", "zh": "金色", "ipa": ""},
      {"es": "plateado", "zh": "銀色", "ipa": ""},
      {"es": "claro", "zh": "淺色的", "ipa": ""},
      {"es": "oscuro", "zh": "深色的", "ipa": ""}
    ],
    "時間與日期": [
      {"es": "tiempo", "zh": "時間", "ipa": ""},
      {"es": "hora", "zh": "小時", "ipa": ""},
      {"es": "minuto", "zh": "分鐘", "ipa": ""},
      {"es": "segundo", "zh": "秒", "ipa": ""},
      {"es": "día", "zh": "日子/天", "ipa": ""},
      {"es": "semana", "zh": "星期", "ipa": ""},
      {"es": "mes", "zh": "月", "ipa": ""},
      {"es": "año", "zh": "年", "ipa": ""},
      {"es": "hoy", "zh": "今天", "ipa": ""},
      {"es": "ayer", "zh": "昨天", "ipa": ""},
      {"es": "mañana", "zh": "明天/早上", "ipa": ""},
      {"es": "ahora", "zh": "現在", "ipa": ""},
      {"es": "después", "zh": "之後", "ipa": ""},
      {"es": "antes", "zh": "之前", "ipa": ""},
      {"es": "siempre", "zh": "總是", "ipa": ""},
      {"es": "nunca", "zh": "從不", "ipa": ""},
      {"es": "a veces", "zh": "有時", "ipa": ""},
      {"es": "temprano", "zh": "早", "ipa": ""},
      {"es": "tarde", "zh": "晚/下午", "ipa": ""},
      {"es": "noche", "zh": "夜晚", "ipa": ""},
      {"es": "madrugada", "zh": "凌晨", "ipa": ""},
      {"es": "mediodía", "zh": "中午", "ipa": ""},
      {"es": "medianoche", "zh": "午夜", "ipa": ""},
      {"es": "lunes", "zh": "星期一", "ipa": ""},
      {"es": "martes", "zh": "星期二", "ipa": ""},
      {"es": "miércoles", "zh": "星期三", "ipa": ""},
      {"es": "jueves", "zh": "星期四", "ipa": ""},
      {"es": "viernes", "zh": "星期五", "ipa": ""},
      {"es": "sábado", "zh": "星期六", "ipa": ""},
      {"es": "domingo", "zh": "星期日", "ipa": ""},
      {"es": "enero", "zh": "一月", "ipa": ""},
      {"es": "febrero", "zh": "二月", "ipa": ""},
      {"es": "marzo", "zh": "三月", "ipa": ""},
      {"es": "abril", "zh": "四月", "ipa": ""},
      {"es": "mayo", "zh": "五月", "ipa": ""},
      {"es": "junio", "zh": "六月", "ipa": ""},
      {"es": "julio", "zh": "七月", "ipa": ""},
      {"es": "agosto", "zh": "八月", "ipa": ""},
      {"es": "septiembre", "zh": "九月", "ipa": ""},
      {"es": "octubre", "zh": "十月", "ipa": ""},
      {"es": "noviembre", "zh": "十一月", "ipa": ""},
      {"es": "diciembre", "zh": "十二月", "ipa": ""},
      {"es": "fin de semana", "zh": "週末", "ipa": ""}
    ],
    "食物與飲料": [
      {"es": "comida", "zh": "食物", "ipa": ""},
      {"es": "desayuno", "zh": "早餐", "ipa": ""},
      {"es": "almuerzo", "zh": "午餐", "ipa": ""},
      {"es": "cena", "zh": "晚餐", "ipa": ""},
      {"es": "agua", "zh": "水", "ipa": ""},
      {"es": "leche", "zh": "牛奶", "ipa": ""},
      {"es": "café", "zh": "咖啡", "ipa": ""},
      {"es": "té", "zh": "茶", "ipa": ""},
      {"es": "jugo", "zh": "果汁", "ipa": ""},
      {"es": "zumo", "zh": "果汁（西班牙）", "ipa": ""},
      {"es": "vino", "zh": "葡萄酒", "ipa": ""},
      {"es": "cerveza", "zh": "啤酒", "ipa": ""},
      {"es": "refresco", "zh": "汽水", "ipa": ""},
      {"es": "pan", "zh": "麵包", "ipa": ""},
      {"es": "arroz", "zh": "米飯", "ipa": ""},
      {"es": "pasta", "zh": "義大利麵", "ipa": ""},
      {"es": "carne", "zh": "肉", "ipa": ""},
      {"es": "pollo", "zh": "雞肉", "ipa": ""},
      {"es": "pescado", "zh": "魚", "ipa": ""},
      {"es": "huevo", "zh": "蛋", "ipa": ""},
      {"es": "queso", "zh": "起司", "ipa": ""},
      {"es": "mantequilla", "zh": "奶油", "ipa": ""},
      {"es": "azúcar", "zh": "糖", "ipa": ""},
      {"es": "sal", "zh": "鹽", "ipa": ""},
      {"es": "pimienta", "zh": "胡椒", "ipa": ""},
      {"es": "aceite", "zh": "油", "ipa": ""},
      {"es": "fruta", "zh": "水果", "ipa": ""},
      {"es": "manzana", "zh": "蘋果", "ipa": ""},
      {"es": "naranja", "zh": "柳橙", "ipa": ""},
      {"es": "plátano", "zh": "香蕉", "ipa": ""},
      {"es": "uva", "zh": "葡萄", "ipa": ""},
      {"es": "fresa", "zh": "草莓", "ipa": ""},
      {"es": "limón", "zh": "檸檬", "ipa": ""},
      {"es": "sandía", "zh": "西瓜", "ipa": ""},
      {"es": "verdura", "zh": "蔬菜", "ipa": ""},
      {"es": "tomate", "zh": "番茄", "ipa": ""},
      {"es": "papa", "zh": "馬鈴薯（拉美）", "ipa": ""},
      {"es": "patata", "zh": "馬鈴薯（西班牙）", "ipa": ""},
      {"es": "cebolla", "zh": "洋蔥", "ipa": ""},
      {"es": "ajo", "zh": "蒜", "ipa": ""},
      {"es": "lechuga", "zh": "萵苣", "ipa": ""},
      {"es": "zanahoria", "zh": "胡蘿蔔", "ipa": ""},
      {"es": "postre", "zh": "甜點", "ipa": ""},
      {"es": "helado", "zh": "冰淇淋", "ipa": ""},
      {"es": "chocolate", "zh": "巧克力", "ipa": ""},
      {"es": "galleta", "zh": "餅乾", "ipa": ""},
      {"es": "pastel", "zh": "蛋糕", "ipa": ""},
      {"es": "sopa", "zh": "湯", "ipa": ""},
      {"es": "ensalada", "zh": "沙拉", "ipa": ""},
      {"es": "hamburguesa", "zh": "漢堡", "ipa": ""}
    ],
    "身體與健康": [
      {"es": "cuerpo", "zh": "身體", "ipa": ""},
      {"es": "cabeza", "zh": "頭", "ipa": ""},
      {"es": "cara", "zh": "臉", "ipa": ""},
      {"es": "ojo", "zh": "眼睛", "ipa": ""},
      {"es": "nariz", "zh": "鼻子", "ipa": ""},
      {"es": "boca", "zh": "嘴", "ipa": ""},
      {"es": "oreja", "zh": "耳朵", "ipa": ""},
      {"es": "diente", "zh": "牙齒", "ipa": ""},
      {"es": "lengua", "zh": "舌頭/語言", "ipa": ""},
      {"es": "pelo", "zh": "頭髮", "ipa": ""},
      {"es": "cuello", "zh": "脖子", "ipa": ""},
      {"es": "hombro", "zh": "肩膀", "ipa": ""},
      {"es": "brazo", "zh": "手臂", "ipa": ""},
      {"es": "mano", "zh": "手", "ipa": ""},
      {"es": "dedo", "zh": "手指", "ipa": ""},
      {"es": "pecho", "zh": "胸", "ipa": ""},
      {"es": "espalda", "zh": "背", "ipa": ""},
      {"es": "estómago", "zh": "胃", "ipa": ""},
      {"es": "pierna", "zh": "腿", "ipa": ""},
      {"es": "rodilla", "zh": "膝蓋", "ipa": ""},
      {"es": "pie", "zh": "腳", "ipa": ""},
      {"es": "corazón", "zh": "心臟", "ipa": ""},
      {"es": "salud", "zh": "健康", "ipa": ""},
      {"es": "enfermo", "zh": "生病的", "ipa": ""},
      {"es": "dolor", "zh": "疼痛", "ipa": ""},
      {"es": "medicina", "zh": "藥", "ipa": ""},
      {"es": "médico", "zh": "醫生", "ipa": ""},
      {"es": "hospital", "zh": "醫院", "ipa": ""},
      {"es": "fiebre", "zh": "發燒", "ipa": ""},
      {"es": "gripe", "zh": "感冒/流感", "ipa": ""}
    ],
    "衣物": [
      {"es": "ropa", "zh": "衣服", "ipa": ""},
      {"es": "camisa", "zh": "襯衫", "ipa": ""},
      {"es": "camiseta", "zh": "T 恤", "ipa": ""},
      {"es": "pantalón", "zh": "褲子", "ipa": ""},
      {"es": "falda", "zh": "裙子", "ipa": ""},
      {"es": "vestido", "zh": "洋裝", "ipa": ""},
      {"es": "chaqueta", "zh": "外套", "ipa": ""},
      {"es": "abrigo", "zh": "大衣", "ipa": ""},
      {"es": "zapatos", "zh": "鞋子", "ipa": ""},
      {"es": "calcetines", "zh": "襪子", "ipa": ""},
      {"es": "sombrero", "zh": "帽子", "ipa": ""},
      {"es": "gorra", "zh": "鴨舌帽", "ipa": ""},
      {"es": "gafas", "zh": "眼鏡", "ipa": ""},
      {"es": "bolso", "zh": "包包", "ipa": ""},
      {"es": "reloj", "zh": "手錶", "ipa": ""},
      {"es": "cinturón", "zh": "皮帶", "ipa": ""},
      {"es": "corbata", "zh": "領帶", "ipa": ""},
      {"es": "bufanda", "zh": "圍巾", "ipa": ""},
      {"es": "guantes", "zh": "手套", "ipa": ""},
      {"es": "traje", "zh": "西裝", "ipa": ""}
    ],
    "家與住所": [
      {"es": "casa", "zh": "家/房子", "ipa": ""},
      {"es": "piso", "zh": "公寓/樓層", "ipa": ""},
      {"es": "apartamento", "zh": "公寓", "ipa": ""},
      {"es": "habitación", "zh": "房間", "ipa": ""},
      {"es": "dormitorio", "zh": "臥室", "ipa": ""},
      {"es": "sala", "zh": "客廳", "ipa": ""},
      {"es": "cocina", "zh": "廚房", "ipa": ""},
      {"es": "baño", "zh": "浴室", "ipa": ""},
      {"es": "comedor", "zh": "飯廳", "ipa": ""},
      {"es": "balcón", "zh": "陽台", "ipa": ""},
      {"es": "jardín", "zh": "花園", "ipa": ""},
      {"es": "garaje", "zh": "車庫", "ipa": ""},
      {"es": "puerta", "zh": "門", "ipa": ""},
      {"es": "ventana", "zh": "窗戶", "ipa": ""},
      {"es": "pared", "zh": "牆", "ipa": ""},
      {"es": "techo", "zh": "天花板/屋頂", "ipa": ""},
      {"es": "suelo", "zh": "地板", "ipa": ""},
      {"es": "escalera", "zh": "樓梯", "ipa": ""},
      {"es": "mesa", "zh": "桌子", "ipa": ""},
      {"es": "silla", "zh": "椅子", "ipa": ""},
      {"es": "cama", "zh": "床", "ipa": ""},
      {"es": "sofá", "zh": "沙發", "ipa": ""},
      {"es": "lámpara", "zh": "燈", "ipa": ""},
      {"es": "espejo", "zh": "鏡子", "ipa": ""},
      {"es": "armario", "zh": "衣櫥", "ipa": ""},
      {"es": "nevera", "zh": "冰箱", "ipa": ""},
      {"es": "horno", "zh": "烤箱", "ipa": ""},
      {"es": "televisión", "zh": "電視", "ipa": ""},
      {"es": "teléfono", "zh": "電話", "ipa": ""},
      {"es": "ordenador", "zh": "電腦（西班牙）", "ipa": ""},
      {"es": "computadora", "zh": "電腦（拉美）", "ipa": ""},
      {"es": "llave", "zh": "鑰匙", "ipa": ""}
    ],
    "動物": [
      {"es": "animal", "zh": "動物", "ipa": ""},
      {"es": "perro", "zh": "狗", "ipa": ""},
      {"es": "gato", "zh": "貓", "ipa": ""},
      {"es": "pájaro", "zh": "鳥", "ipa": ""},
      {"es": "pez", "zh": "魚（活的）", "ipa": ""},
      {"es": "caballo", "zh": "馬", "ipa": ""},
      {"es": "vaca", "zh": "牛", "ipa": ""},
      {"es": "cerdo", "zh": "豬", "ipa": ""},
      {"es": "oveja", "zh": "羊", "ipa": ""},
      {"es": "gallina", "zh": "母雞", "ipa": ""},
      {"es": "ratón", "zh": "老鼠", "ipa": ""},
      {"es": "conejo", "zh": "兔子", "ipa": ""},
      {"es": "elefante", "zh": "大象", "ipa": ""},
      {"es": "león", "zh": "獅子", "ipa": ""},
      {"es": "tigre", "zh": "老虎", "ipa": ""},
      {"es": "oso", "zh": "熊", "ipa": ""},
      {"es": "mono", "zh": "猴子", "ipa": ""},
      {"es": "serpiente", "zh": "蛇", "ipa": ""},
      {"es": "araña", "zh": "蜘蛛", "ipa": ""},
      {"es": "mariposa", "zh": "蝴蝶", "ipa": ""}
    ],
    "交通與旅行": [
      {"es": "coche", "zh": "汽車（西班牙）", "ipa": ""},
      {"es": "carro", "zh": "汽車（拉美）", "ipa": ""},
      {"es": "autobús", "zh": "公車", "ipa": ""},
      {"es": "tren", "zh": "火車", "ipa": ""},
      {"es": "avión", "zh": "飛機", "ipa": ""},
      {"es": "barco", "zh": "船", "ipa": ""},
      {"es": "bicicleta", "zh": "腳踏車", "ipa": ""},
      {"es": "motocicleta", "zh": "摩托車", "ipa": ""},
      {"es": "taxi", "zh": "計程車", "ipa": ""},
      {"es": "metro", "zh": "捷運/地鐵", "ipa": ""},
      {"es": "estación", "zh": "車站", "ipa": ""},
      {"es": "aeropuerto", "zh": "機場", "ipa": ""},
      {"es": "puerto", "zh": "港口", "ipa": ""},
      {"es": "parada", "zh": "站牌", "ipa": ""},
      {"es": "billete", "zh": "票（西班牙）", "ipa": ""},
      {"es": "boleto", "zh": "票（拉美）", "ipa": ""},
      {"es": "maleta", "zh": "行李箱", "ipa": ""},
      {"es": "pasaporte", "zh": "護照", "ipa": ""},
      {"es": "viaje", "zh": "旅行", "ipa": ""},
      {"es": "vacaciones", "zh": "假期", "ipa": ""},
      {"es": "hotel", "zh": "飯店", "ipa": ""},
      {"es": "habitación", "zh": "房間", "ipa": ""},
      {"es": "calle", "zh": "街道", "ipa": ""},
      {"es": "avenida", "zh": "大道", "ipa": ""},
      {"es": "plaza", "zh": "廣場", "ipa": ""},
      {"es": "puente", "zh": "橋", "ipa": ""},
      {"es": "carretera", "zh": "公路", "ipa": ""},
      {"es": "mapa", "zh": "地圖", "ipa": ""},
      {"es": "playa", "zh": "海灘", "ipa": ""},
      {"es": "montaña", "zh": "山", "ipa": ""}
    ],
    "城市與場所": [
      {"es": "ciudad", "zh": "城市", "ipa": ""},
      {"es": "pueblo", "zh": "小鎮", "ipa": ""},
      {"es": "país", "zh": "國家", "ipa": ""},
      {"es": "mundo", "zh": "世界", "ipa": ""},
      {"es": "lugar", "zh": "地方", "ipa": ""},
      {"es": "escuela", "zh": "學校", "ipa": ""},
      {"es": "universidad", "zh": "大學", "ipa": ""},
      {"es": "oficina", "zh": "辦公室", "ipa": ""},
      {"es": "tienda", "zh": "商店", "ipa": ""},
      {"es": "supermercado", "zh": "超市", "ipa": ""},
      {"es": "mercado", "zh": "市場", "ipa": ""},
      {"es": "restaurante", "zh": "餐廳", "ipa": ""},
      {"es": "cafetería", "zh": "咖啡廳", "ipa": ""},
      {"es": "bar", "zh": "酒吧", "ipa": ""},
      {"es": "banco", "zh": "銀行/長椅", "ipa": ""},
      {"es": "iglesia", "zh": "教堂", "ipa": ""},
      {"es": "museo", "zh": "博物館", "ipa": ""},
      {"es": "biblioteca", "zh": "圖書館", "ipa": ""},
      {"es": "parque", "zh": "公園", "ipa": ""},
      {"es": "cine", "zh": "電影院", "ipa": ""},
      {"es": "teatro", "zh": "劇院", "ipa": ""},
      {"es": "farmacia", "zh": "藥局", "ipa": ""},
      {"es": "panadería", "zh": "麵包店", "ipa": ""},
      {"es": "gimnasio", "zh": "健身房", "ipa": ""},
      {"es": "iglesia", "zh": "教堂", "ipa": ""}
    ],
    "職業": [
      {"es": "trabajo", "zh": "工作", "ipa": ""},
      {"es": "profesión", "zh": "職業", "ipa": ""},
      {"es": "profesor", "zh": "老師（男）", "ipa": ""},
      {"es": "profesora", "zh": "老師（女）", "ipa": ""},
      {"es": "estudiante", "zh": "學生", "ipa": ""},
      {"es": "médico", "zh": "醫生", "ipa": ""},
      {"es": "enfermero", "zh": "護理師", "ipa": ""},
      {"es": "abogado", "zh": "律師", "ipa": ""},
      {"es": "ingeniero", "zh": "工程師", "ipa": ""},
      {"es": "arquitecto", "zh": "建築師", "ipa": ""},
      {"es": "cocinero", "zh": "廚師", "ipa": ""},
      {"es": "camarero", "zh": "服務生", "ipa": ""},
      {"es": "policía", "zh": "警察", "ipa": ""},
      {"es": "bombero", "zh": "消防員", "ipa": ""},
      {"es": "artista", "zh": "藝術家", "ipa": ""},
      {"es": "actor", "zh": "演員", "ipa": ""},
      {"es": "cantante", "zh": "歌手", "ipa": ""},
      {"es": "escritor", "zh": "作家", "ipa": ""},
      {"es": "periodista", "zh": "記者", "ipa": ""},
      {"es": "conductor", "zh": "司機", "ipa": ""},
      {"es": "vendedor", "zh": "業務員", "ipa": ""},
      {"es": "secretario", "zh": "秘書", "ipa": ""},
      {"es": "jefe", "zh": "老闆/主管", "ipa": ""},
      {"es": "empresario", "zh": "企業家", "ipa": ""},
      {"es": "trabajador", "zh": "工人/員工", "ipa": ""}
    ],
    "形容詞": [
      {"es": "grande", "zh": "大的", "ipa": ""},
      {"es": "pequeño", "zh": "小的", "ipa": ""},
      {"es": "alto", "zh": "高的", "ipa": ""},
      {"es": "bajo", "zh": "矮/低的", "ipa": ""},
      {"es": "largo", "zh": "長的", "ipa": ""},
      {"es": "corto", "zh": "短的", "ipa": ""},
      {"es": "ancho", "zh": "寬的", "ipa": ""},
      {"es": "estrecho", "zh": "窄的", "ipa": ""},
      {"es": "gordo", "zh": "胖的", "ipa": ""},
      {"es": "delgado", "zh": "瘦的", "ipa": ""},
      {"es": "joven", "zh": "年輕的", "ipa": ""},
      {"es": "viejo", "zh": "老的/舊的", "ipa": ""},
      {"es": "nuevo", "zh": "新的", "ipa": ""},
      {"es": "bueno", "zh": "好的", "ipa": ""},
      {"es": "malo", "zh": "壞的", "ipa": ""},
      {"es": "mejor", "zh": "更好的", "ipa": ""},
      {"es": "peor", "zh": "更壞的", "ipa": ""},
      {"es": "bonito", "zh": "漂亮的", "ipa": ""},
      {"es": "guapo", "zh": "帥/美的", "ipa": ""},
      {"es": "feo", "zh": "醜的", "ipa": ""},
      {"es": "fácil", "zh": "簡單的", "ipa": ""},
      {"es": "difícil", "zh": "困難的", "ipa": ""},
      {"es": "rápido", "zh": "快的", "ipa": ""},
      {"es": "lento", "zh": "慢的", "ipa": ""},
      {"es": "caro", "zh": "貴的", "ipa": ""},
      {"es": "barato", "zh": "便宜的", "ipa": ""},
      {"es": "rico", "zh": "有錢的/好吃的", "ipa": ""},
      {"es": "pobre", "zh": "窮的", "ipa": ""},
      {"es": "feliz", "zh": "快樂的", "ipa": ""},
      {"es": "triste", "zh": "難過的", "ipa": ""},
      {"es": "cansado", "zh": "累的", "ipa": ""},
      {"es": "enfadado", "zh": "生氣的", "ipa": ""},
      {"es": "tranquilo", "zh": "平靜的", "ipa": ""},
      {"es": "nervioso", "zh": "緊張的", "ipa": ""},
      {"es": "ocupado", "zh": "忙的", "ipa": ""},
      {"es": "aburrido", "zh": "無聊的", "ipa": ""},
      {"es": "interesante", "zh": "有趣的", "ipa": ""},
      {"es": "importante", "zh": "重要的", "ipa": ""},
      {"es": "famoso", "zh": "有名的", "ipa": ""},
      {"es": "fuerte", "zh": "強壯的", "ipa": ""},
      {"es": "débil", "zh": "虛弱的", "ipa": ""},
      {"es": "limpio", "zh": "乾淨的", "ipa": ""},
      {"es": "sucio", "zh": "髒的", "ipa": ""},
      {"es": "caliente", "zh": "熱的", "ipa": ""},
      {"es": "frío", "zh": "冷的", "ipa": ""},
      {"es": "duro", "zh": "硬的", "ipa": ""},
      {"es": "blando", "zh": "軟的", "ipa": ""},
      {"es": "lleno", "zh": "滿的/飽的", "ipa": ""},
      {"es": "vacío", "zh": "空的", "ipa": ""},
      {"es": "abierto", "zh": "開著的", "ipa": ""},
      {"es": "cerrado", "zh": "關著的", "ipa": ""}
    ],
    "常用動詞": [
      {"es": "ser", "zh": "是（本質）", "ipa": ""},
      {"es": "estar", "zh": "是（狀態/位置）", "ipa": ""},
      {"es": "tener", "zh": "有", "ipa": ""},
      {"es": "hay", "zh": "有（存在）", "ipa": ""},
      {"es": "haber", "zh": "有（助動詞）", "ipa": ""},
      {"es": "hacer", "zh": "做", "ipa": ""},
      {"es": "ir", "zh": "去", "ipa": ""},
      {"es": "venir", "zh": "來", "ipa": ""},
      {"es": "ver", "zh": "看見", "ipa": ""},
      {"es": "mirar", "zh": "看（注視）", "ipa": ""},
      {"es": "oír", "zh": "聽到", "ipa": ""},
      {"es": "escuchar", "zh": "聽（專注）", "ipa": ""},
      {"es": "hablar", "zh": "說話", "ipa": ""},
      {"es": "decir", "zh": "說（內容）", "ipa": ""},
      {"es": "preguntar", "zh": "問", "ipa": ""},
      {"es": "responder", "zh": "回答", "ipa": ""},
      {"es": "leer", "zh": "讀", "ipa": ""},
      {"es": "escribir", "zh": "寫", "ipa": ""},
      {"es": "estudiar", "zh": "學習/讀書", "ipa": ""},
      {"es": "aprender", "zh": "學會", "ipa": ""},
      {"es": "enseñar", "zh": "教", "ipa": ""},
      {"es": "entender", "zh": "理解", "ipa": ""},
      {"es": "saber", "zh": "知道（知識）", "ipa": ""},
      {"es": "conocer", "zh": "認識（人/地）", "ipa": ""},
      {"es": "pensar", "zh": "思考/認為", "ipa": ""},
      {"es": "creer", "zh": "相信", "ipa": ""},
      {"es": "querer", "zh": "想要/愛", "ipa": ""},
      {"es": "amar", "zh": "愛", "ipa": ""},
      {"es": "gustar", "zh": "喜歡", "ipa": ""},
      {"es": "preferir", "zh": "偏好", "ipa": ""},
      {"es": "necesitar", "zh": "需要", "ipa": ""},
      {"es": "deber", "zh": "應當/欠", "ipa": ""},
      {"es": "poder", "zh": "能夠", "ipa": ""},
      {"es": "dar", "zh": "給", "ipa": ""},
      {"es": "recibir", "zh": "接收", "ipa": ""},
      {"es": "coger", "zh": "拿（西班牙）", "ipa": ""},
      {"es": "tomar", "zh": "拿/喝（拉美）", "ipa": ""},
      {"es": "llevar", "zh": "帶/穿", "ipa": ""},
      {"es": "traer", "zh": "帶來", "ipa": ""},
      {"es": "comer", "zh": "吃", "ipa": ""},
      {"es": "beber", "zh": "喝", "ipa": ""},
      {"es": "dormir", "zh": "睡", "ipa": ""},
      {"es": "despertar", "zh": "醒來", "ipa": ""},
      {"es": "vivir", "zh": "住/活", "ipa": ""},
      {"es": "morir", "zh": "死", "ipa": ""},
      {"es": "trabajar", "zh": "工作", "ipa": ""},
      {"es": "comprar", "zh": "買", "ipa": ""},
      {"es": "vender", "zh": "賣", "ipa": ""},
      {"es": "pagar", "zh": "付錢", "ipa": ""},
      {"es": "costar", "zh": "花費", "ipa": ""},
      {"es": "abrir", "zh": "打開", "ipa": ""},
      {"es": "cerrar", "zh": "關閉", "ipa": ""},
      {"es": "empezar", "zh": "開始", "ipa": ""},
      {"es": "comenzar", "zh": "開始", "ipa": ""},
      {"es": "terminar", "zh": "結束", "ipa": ""},
      {"es": "acabar", "zh": "結束", "ipa": ""},
      {"es": "seguir", "zh": "繼續/跟隨", "ipa": ""},
      {"es": "esperar", "zh": "等待/希望", "ipa": ""},
      {"es": "buscar", "zh": "找", "ipa": ""},
      {"es": "encontrar", "zh": "找到", "ipa": ""},
      {"es": "perder", "zh": "失去/迷路", "ipa": ""},
      {"es": "ganar", "zh": "贏/賺", "ipa": ""},
      {"es": "jugar", "zh": "玩", "ipa": ""},
      {"es": "cantar", "zh": "唱歌", "ipa": ""},
      {"es": "bailar", "zh": "跳舞", "ipa": ""},
      {"es": "correr", "zh": "跑", "ipa": ""},
      {"es": "caminar", "zh": "走路", "ipa": ""},
      {"es": "andar", "zh": "走/運轉", "ipa": ""},
      {"es": "subir", "zh": "上升/上去", "ipa": ""},
      {"es": "bajar", "zh": "下降/下去", "ipa": ""},
      {"es": "salir", "zh": "出去/離開", "ipa": ""},
      {"es": "entrar", "zh": "進入", "ipa": ""},
      {"es": "llegar", "zh": "到達", "ipa": ""},
      {"es": "volver", "zh": "回來", "ipa": ""},
      {"es": "ayudar", "zh": "幫助", "ipa": ""},
      {"es": "trabajar", "zh": "工作", "ipa": ""},
      {"es": "descansar", "zh": "休息", "ipa": ""},
      {"es": "viajar", "zh": "旅行", "ipa": ""},
      {"es": "visitar", "zh": "拜訪", "ipa": ""},
      {"es": "llamar", "zh": "打電話/叫", "ipa": ""},
      {"es": "llamarse", "zh": "名叫", "ipa": ""},
      {"es": "conocer", "zh": "認識", "ipa": ""},
      {"es": "recordar", "zh": "記得", "ipa": ""},
      {"es": "olvidar", "zh": "忘記", "ipa": ""},
      {"es": "sentir", "zh": "感覺", "ipa": ""},
      {"es": "reír", "zh": "笑", "ipa": ""},
      {"es": "llorar", "zh": "哭", "ipa": ""},
      {"es": "ducharse", "zh": "洗澡", "ipa": ""},
      {"es": "lavarse", "zh": "清洗（自己）", "ipa": ""},
      {"es": "vestirse", "zh": "穿衣", "ipa": ""},
      {"es": "levantarse", "zh": "起床", "ipa": ""},
      {"es": "acostarse", "zh": "上床睡覺", "ipa": ""},
      {"es": "sentarse", "zh": "坐下", "ipa": ""},
      {"es": "casarse", "zh": "結婚", "ipa": ""},
      {"es": "divertirse", "zh": "玩得開心", "ipa": ""}
    ],
    "天氣與自然": [
      {"es": "tiempo", "zh": "天氣/時間", "ipa": ""},
      {"es": "clima", "zh": "氣候", "ipa": ""},
      {"es": "sol", "zh": "太陽", "ipa": ""},
      {"es": "luna", "zh": "月亮", "ipa": ""},
      {"es": "estrella", "zh": "星星", "ipa": ""},
      {"es": "cielo", "zh": "天空", "ipa": ""},
      {"es": "nube", "zh": "雲", "ipa": ""},
      {"es": "lluvia", "zh": "雨", "ipa": ""},
      {"es": "nieve", "zh": "雪", "ipa": ""},
      {"es": "viento", "zh": "風", "ipa": ""},
      {"es": "tormenta", "zh": "暴風雨", "ipa": ""},
      {"es": "calor", "zh": "熱", "ipa": ""},
      {"es": "frío", "zh": "冷", "ipa": ""},
      {"es": "primavera", "zh": "春天", "ipa": ""},
      {"es": "verano", "zh": "夏天", "ipa": ""},
      {"es": "otoño", "zh": "秋天", "ipa": ""},
      {"es": "invierno", "zh": "冬天", "ipa": ""},
      {"es": "árbol", "zh": "樹", "ipa": ""},
      {"es": "flor", "zh": "花", "ipa": ""},
      {"es": "hoja", "zh": "葉子", "ipa": ""},
      {"es": "río", "zh": "河", "ipa": ""},
      {"es": "lago", "zh": "湖", "ipa": ""},
      {"es": "mar", "zh": "海", "ipa": ""},
      {"es": "isla", "zh": "島", "ipa": ""},
      {"es": "bosque", "zh": "森林", "ipa": ""},
      {"es": "tierra", "zh": "土地/地球", "ipa": ""},
      {"es": "fuego", "zh": "火", "ipa": ""},
      {"es": "naturaleza", "zh": "自然", "ipa": ""}
    ],
    "疑問詞與連接詞": [
      {"es": "qué", "zh": "什麼", "ipa": ""},
      {"es": "quién", "zh": "誰", "ipa": ""},
      {"es": "cuándo", "zh": "何時", "ipa": ""},
      {"es": "dónde", "zh": "哪裡", "ipa": ""},
      {"es": "cómo", "zh": "如何", "ipa": ""},
      {"es": "por qué", "zh": "為什麼", "ipa": ""},
      {"es": "cuánto", "zh": "多少", "ipa": ""},
      {"es": "cuál", "zh": "哪一個", "ipa": ""},
      {"es": "y", "zh": "和", "ipa": ""},
      {"es": "o", "zh": "或", "ipa": ""},
      {"es": "pero", "zh": "但是", "ipa": ""},
      {"es": "porque", "zh": "因為", "ipa": ""},
      {"es": "si", "zh": "如果", "ipa": ""},
      {"es": "sí", "zh": "是", "ipa": ""},
      {"es": "no", "zh": "不", "ipa": ""},
      {"es": "muy", "zh": "很", "ipa": ""},
      {"es": "mucho", "zh": "很多", "ipa": ""},
      {"es": "poco", "zh": "少", "ipa": ""},
      {"es": "también", "zh": "也", "ipa": ""},
      {"es": "tampoco", "zh": "也不", "ipa": ""},
      {"es": "ya", "zh": "已經", "ipa": ""},
      {"es": "todavía", "zh": "還", "ipa": ""},
      {"es": "aunque", "zh": "雖然", "ipa": ""},
      {"es": "entonces", "zh": "那麼", "ipa": ""},
      {"es": "luego", "zh": "然後", "ipa": ""}
    ],
    "其他常用名詞": [
      {"es": "cosa", "zh": "東西", "ipa": ""},
      {"es": "dinero", "zh": "錢", "ipa": ""},
      {"es": "vida", "zh": "生活/生命", "ipa": ""},
      {"es": "muerte", "zh": "死亡", "ipa": ""},
      {"es": "nombre", "zh": "名字", "ipa": ""},
      {"es": "edad", "zh": "年齡", "ipa": ""},
      {"es": "idea", "zh": "想法", "ipa": ""},
      {"es": "problema", "zh": "問題", "ipa": ""},
      {"es": "pregunta", "zh": "問題（疑問）", "ipa": ""},
      {"es": "respuesta", "zh": "答案", "ipa": ""},
      {"es": "razón", "zh": "理由", "ipa": ""},
      {"es": "verdad", "zh": "真理/事實", "ipa": ""},
      {"es": "mentira", "zh": "謊言", "ipa": ""},
      {"es": "amor", "zh": "愛", "ipa": ""},
      {"es": "amistad", "zh": "友誼", "ipa": ""},
      {"es": "fiesta", "zh": "派對", "ipa": ""},
      {"es": "regalo", "zh": "禮物", "ipa": ""},
      {"es": "cumpleaños", "zh": "生日", "ipa": ""},
      {"es": "boda", "zh": "婚禮", "ipa": ""},
      {"es": "trabajo", "zh": "工作", "ipa": ""},
      {"es": "música", "zh": "音樂", "ipa": ""},
      {"es": "canción", "zh": "歌曲", "ipa": ""},
      {"es": "película", "zh": "電影", "ipa": ""},
      {"es": "libro", "zh": "書", "ipa": ""},
      {"es": "periódico", "zh": "報紙", "ipa": ""},
      {"es": "revista", "zh": "雜誌", "ipa": ""},
      {"es": "carta", "zh": "信", "ipa": ""},
      {"es": "papel", "zh": "紙", "ipa": ""},
      {"es": "número", "zh": "數字/號碼", "ipa": ""},
      {"es": "deporte", "zh": "運動", "ipa": ""},
      {"es": "fútbol", "zh": "足球", "ipa": ""},
      {"es": "juego", "zh": "遊戲", "ipa": ""},
      {"es": "lengua", "zh": "語言/舌頭", "ipa": ""},
      {"es": "idioma", "zh": "語言", "ipa": ""},
      {"es": "palabra", "zh": "詞", "ipa": ""},
      {"es": "historia", "zh": "歷史/故事", "ipa": ""},
      {"es": "ejemplo", "zh": "例子", "ipa": ""},
      {"es": "información", "zh": "資訊", "ipa": ""},
      {"es": "noticia", "zh": "新聞", "ipa": ""},
      {"es": "foto", "zh": "照片", "ipa": ""},
      {"es": "imagen", "zh": "圖像", "ipa": ""}
    ]
  }
}
